plain/redirection/CHANGELOG.md
plain/redirection/README.md
plain/redirection/__init__.py
plain/redirection/admin.py
plain/redirection/chores.py
plain/redirection/config.py
plain/redirection/default_settings.py
plain/redirection/middleware.py
plain/redirection/models.py
plain/redirection/migrations/0001_initial.py
plain/redirection/migrations/__init__.py
plain/redirection/templates/admin/plainredirection/redirect_form.html
plain_redirection-0.31.0.dist-info/METADATA
plain_redirection-0.31.0.dist-info/WHEEL
plain_redirection-0.31.0.dist-info/licenses/LICENSE
plain_redirection-0.31.0.dist-info/RECORD
