Metadata-Version: 2.4
Name: plain.redirection
Version: 0.31.0
Summary: A flexible URL redirection system with admin interface and logging.
Author-email: Dave Gaeddert <dave.gaeddert@dropseed.dev>
License-Expression: BSD-3-Clause
License-File: LICENSE
Requires-Python: >=3.13
Requires-Dist: plain-models<1.0.0
Requires-Dist: plain<1.0.0
